chkdns/__init__.py
chkdns/app.py
chkdns/stats.py
chkdns/types.py
chkdns/whatsmydns/__init__.py
chkdns/whatsmydns/client.py
chkdns/whatsmydns/mocks.py
chkdns/whatsmydns/servers.py
chkdns-0.4.0.dist-info/entry_points.txt
chkdns-0.4.0.dist-info/LICENSE
chkdns-0.4.0.dist-info/WHEEL
chkdns-0.4.0.dist-info/METADATA
chkdns-0.4.0.dist-info/RECORD
